{
  "updated": "2026-06-28T19:55:24.525294+00:00",
  "total_indexed": 6556,
  "sources": {
    "Hacker News": {
      "total": 20,
      "new": 17,
      "elapsed": 2.13,
      "last_fetch": "2026-06-28T19:55:19.862418+00:00"
    },
    "Lobsters": {
      "total": 25,
      "new": 8,
      "elapsed": 0.18,
      "last_fetch": "2026-06-28T19:55:20.039315+00:00"
    },
    "Ars Technica": {
      "total": 20,
      "new": 1,
      "elapsed": 0.11,
      "last_fetch": "2026-06-28T19:55:20.151420+00:00"
    },
    "The Verge": {
      "total": 10,
      "new": 2,
      "elapsed": 0.12,
      "last_fetch": "2026-06-28T19:55:20.269465+00:00"
    },
    "BBC News": {
      "total": 45,
      "new": 17,
      "elapsed": 0.23,
      "last_fetch": "2026-06-28T19:55:20.496694+00:00"
    },
    "NPR": {
      "total": 10,
      "new": 4,
      "elapsed": 0.28,
      "last_fetch": "2026-06-28T19:55:20.777928+00:00"
    },
    "TechCrunch": {
      "total": 20,
      "new": 3,
      "elapsed": 0.07,
      "last_fetch": "2026-06-28T19:55:20.851120+00:00"
    },
    "Wired": {
      "total": 50,
      "new": 0,
      "elapsed": 0.12,
      "last_fetch": "2026-06-28T19:55:20.976166+00:00"
    },
    "36Kr": {
      "total": 30,
      "new": 0,
      "elapsed": 1.5,
      "last_fetch": "2026-06-28T19:55:22.471695+00:00"
    },
    "少数派": {
      "total": 10,
      "new": 0,
      "elapsed": 1.31,
      "last_fetch": "2026-06-28T19:55:23.785411+00:00"
    },
    "Science Daily": {
      "total": 60,
      "new": 3,
      "elapsed": 0.13,
      "last_fetch": "2026-06-28T19:55:23.917468+00:00"
    },
    "Nature": {
      "total": 75,
      "new": 0,
      "elapsed": 0.14,
      "last_fetch": "2026-06-28T19:55:24.055240+00:00"
    }
  }
}